dashbored.py
dashbored-1.1.0.dist-info/METADATA
dashbored-1.1.0.dist-info/WHEEL
dashbored-1.1.0.dist-info/top_level.txt
dashbored-1.1.0.dist-info/RECORD
