Metadata-Version: 2.1
Name: dashbored
Version: 1.1.0
Summary: An overly simple dashboard framework
